custom_model/__init__.py
custom_model/linear_model.py
custom_linear_model-0.1.dist-info/METADATA
custom_linear_model-0.1.dist-info/WHEEL
custom_linear_model-0.1.dist-info/entry_points.txt
custom_linear_model-0.1.dist-info/top_level.txt
custom_linear_model-0.1.dist-info/RECORD
