Metadata-Version: 2.1
Name: custom_linear_model
Version: 0.1
Requires-Dist: mlflow >=1.21.0
